README.rst
setup.py
django_randomfields.egg-info/PKG-INFO
django_randomfields.egg-info/SOURCES.txt
django_randomfields.egg-info/dependency_links.txt
django_randomfields.egg-info/requires.txt
django_randomfields.egg-info/top_level.txt
randomfields/__init__.py
randomfields/checks.py
randomfields/random.py
randomfields/forms/__init__.py
randomfields/forms/fields/__init__.py
randomfields/forms/fields/string.py
randomfields/models/__init__.py
randomfields/models/fields/__init__.py
randomfields/models/fields/base.py
randomfields/models/fields/string.py
randomfields/models/fields/integer/__init__.py
randomfields/models/fields/integer/base.py
randomfields/models/fields/integer/identifier.py
randomfields/tests/__init__.py
randomfields/tests/models.py
randomfields/tests/test_identifier_fk.py
randomfields/tests/test_integer_fields.py
randomfields/tests/test_string_fields.py