Metadata-Version: 1.1
Name: django-randomfields
Version: 0.1.9
Summary: Random fields for django models
Home-page: https://github.com/thenewguy/django-randomfields
Author: UNKNOWN
Author-email: UNKNOWN
License: UNKNOWN
Platform: UNKNOWN
Classifier: Programming Language :: Python
Classifier: Operating System :: OS Independent
Classifier: Framework :: Django
